{
  "fractions": [
    {
      "q": "מה גדול יותר: 3/8 או 5/8? (כתבי את השבר הגדול)",
      "a": "5/8",
      "type": "text"
    },
    {
      "q": "מה גדול יותר: 2/7 או 5/7? (כתבי את השבר הגדול)",
      "a": "5/7",
      "type": "text"
    },
    {
      "q": "מה גדול יותר: 1/2 או 1/4? (כתבי את השבר הגדול)",
      "a": "1/2",
      "type": "text"
    },
    {
      "q": "מה קטן יותר: 1/3 או 1/6? (כתבי את השבר הקטן)",
      "a": "1/6",
      "type": "text"
    },
    {
      "q": "מה גדול יותר: 4/10 או 7/10? (כתבי את השבר הגדול)",
      "a": "7/10",
      "type": "text"
    },
    {
      "q": "כתבי < או > או = : 3/8 ___ 5/8",
      "a": "<",
      "type": "text"
    },
    {
      "q": "כתבי < או > או = : 2/7 ___ 2/9",
      "a": ">",
      "type": "text"
    },
    {
      "q": "כתבי < או > או = : 6/6 ___ 10/10",
      "a": "=",
      "type": "text"
    },
    {
      "q": "כתבי < או > או = : 1/2 ___ 1/3",
      "a": ">",
      "type": "text"
    },
    {
      "q": "כתבי < או > או = : 5/8 ___ 7/8",
      "a": "<",
      "type": "text"
    },
    {
      "q": "כתבי < או > או = : 3/4 ___ 2/4",
      "a": ">",
      "type": "text"
    },
    {
      "q": "כתבי < או > או = : 4/5 ___ 4/7",
      "a": ">",
      "type": "text"
    },
    {
      "q": "כתבי < או > או = : 1/6 ___ 1/4",
      "a": "<",
      "type": "text"
    },
    {
      "q": "השלימו: 7/8 > ___/8",
      "a": "6",
      "type": "text"
    },
    {
      "q": "השלימו: ___/5 < 4/5",
      "a": "3",
      "type": "text"
    },
    {
      "q": "השלימו: 1/___ = 9/18",
      "a": "2",
      "type": "text"
    },
    {
      "q": "השלימו: 1/2 > ___/10",
      "a": "4",
      "type": "text"
    },
    {
      "q": "השלימו: ___/7 = 1",
      "a": "7",
      "type": "text"
    },
    {
      "q": "השלימו: 0 = ___/10",
      "a": "0",
      "type": "text"
    },
    {
      "q": "סדרו מהגדול לקטן: 2/7, 4/7, 7/7, 9/7 (הפרידו בפסיקים)",
      "a": "9/7, 7/7, 4/7, 2/7",
      "type": "text"
    },
    {
      "q": "סדרו מהקטן לגדול: 4/6, 4/10, 4/5, 4/3 (הפרידו בפסיקים)",
      "a": "4/10, 4/6, 4/5, 4/3",
      "type": "text"
    },
    {
      "q": "סדרו מהגדול לקטן: 1/2, 5/6, 1/6, 3/6 (הפרידו בפסיקים)",
      "a": "5/6, 1/2, 3/6, 1/6",
      "type": "text"
    },
    {
      "q": "הקיפי את כל הצורות שבהן צבוע חצי (1/2):",
      "type": "shapes",
      "shapes": [
        {"type": "circle", "filled": "half", "id": "c1"},
        {"type": "rectangle", "parts": 4, "filled": 2, "id": "r1"},
        {"type": "circle", "filled": "third", "id": "c2"},
        {"type": "rectangle", "parts": 3, "filled": 1, "id": "r2"},
        {"type": "rectangle", "parts": 2, "filled": 1, "id": "r3"}
      ],
      "correctIds": ["c1", "r1", "r3"]
    },
    {
      "q": "הקיפי את כל הצורות שבהן צבוע שליש (1/3):",
      "type": "shapes",
      "shapes": [
        {"type": "circle", "filled": "third", "id": "c4"},
        {"type": "rectangle", "parts": 3, "filled": 1, "id": "r4"},
        {"type": "circle", "filled": "half", "id": "c5"},
        {"type": "rectangle", "parts": 6, "filled": 2, "id": "r5"},
        {"type": "rectangle", "parts": 4, "filled": 1, "id": "r6"}
      ],
      "correctIds": ["c4", "r4", "r5"]
    },
    {
      "q": "3/8 + 2/8 = ?",
      "a": "5/8",
      "type": "text"
    },
    {
      "q": "7/10 - 3/10 = ?",
      "a": "4/10",
      "type": "text"
    },
    {
      "q": "1 - 1/7 = ?",
      "a": "6/7",
      "type": "text"
    },
    {
      "q": "4/11 + 6/11 = ?",
      "a": "10/11",
      "type": "text"
    },
    {
      "q": "5/9 + 2/9 = ?",
      "a": "7/9",
      "type": "text"
    },
    {
      "q": "8/12 - 3/12 = ?",
      "a": "5/12",
      "type": "text"
    },
    {
      "q": "2/5 + 2/5 = ?",
      "a": "4/5",
      "type": "text"
    },
    {
      "q": "9/10 - 4/10 = ?",
      "a": "5/10",
      "type": "text"
    },
    {
      "q": "1/6 + 4/6 = ?",
      "a": "5/6",
      "type": "text"
    },
    {
      "q": "7/8 - 2/8 = ?",
      "a": "5/8",
      "type": "text"
    },
    {
      "q": "3/7 + 3/7 = ?",
      "a": "6/7",
      "type": "text"
    },
    {
      "q": "6/10 - 2/10 = ?",
      "a": "4/10",
      "type": "text"
    },
    {
      "q": "3/4 × 4 = ?",
      "a": "3",
      "type": "text"
    },
    {
      "q": "7 × 1/7 = ?",
      "a": "1",
      "type": "text"
    },
    {
      "q": "2/5 × 5 = ?",
      "a": "2",
      "type": "text"
    },
    {
      "q": "6 × 1/6 = ?",
      "a": "1",
      "type": "text"
    },
    {
      "q": "1/8 × 8 = ?",
      "a": "1",
      "type": "text"
    },
    {
      "q": "4 × 2/4 = ?",
      "a": "2",
      "type": "text"
    },
    {
      "q": "5 × 3/5 = ?",
      "a": "3",
      "type": "text"
    },
    {
      "q": "1/3 × 6 = ?",
      "a": "2",
      "type": "text"
    },
    {
      "q": "8 × 1/8 = ?",
      "a": "1",
      "type": "text"
    },
    {
      "q": "3 × 2/3 = ?",
      "a": "2",
      "type": "text"
    },
    {
      "q": "בעוגה יש 10 פרוסות. אניה אכלה 2 פרוסות. איזה חלק אכלה? (כתבי בצורת שבר)",
      "a": "2/10",
      "type": "text"
    },
    {
      "q": "בכיתה יש 8 ילדים. 3 מהם בנים. איזה חלק מהכיתה הם בנים? (כתבי בצורת שבר)",
      "a": "3/8",
      "type": "text"
    },
    {
      "q": "בסל יש 12 תפוחים. 5 מהם אדומים. איזה חלק אדום? (כתבי בצורת שבר)",
      "a": "5/12",
      "type": "text"
    },
    {
      "q": "בצנצנת יש 7 סוכריות. אכלתי 2. איזה חלק אכלתי? (כתבי בצורת שבר)",
      "a": "2/7",
      "type": "text"
    },
    {
      "q": "בגן יש 9 פרחים. 4 מהם צהובים. איזה חלק צהוב? (כתבי בצורת שבר)",
      "a": "4/9",
      "type": "text"
    },
    {
      "q": "במבחן היו 20 שאלות. ענתי נכון על 15. איזה חלק ענתה נכון? (כתבי בצורת שבר)",
      "a": "15/20",
      "type": "text"
    }
  ],
  "operations": [
    {
      "q": "48 × 10 = ?",
      "a": "480",
      "type": "text"
    },
    {
      "q": "501 × 100 = ?",
      "a": "50100",
      "type": "text"
    },
    {
      "q": "123 × 10 = ?",
      "a": "1230",
      "type": "text"
    },
    {
      "q": "3,800 ÷ 10 = ?",
      "a": "380",
      "type": "text"
    },
    {
      "q": "5,000 ÷ 100 = ?",
      "a": "50",
      "type": "text"
    },
    {
      "q": "2,030 × 10 = ?",
      "a": "20300",
      "type": "text"
    },
    {
      "q": "67 × 100 = ?",
      "a": "6700",
      "type": "text"
    },
    {
      "q": "9,400 ÷ 10 = ?",
      "a": "940",
      "type": "text"
    },
    {
      "q": "235 × 1000 = ?",
      "a": "235000",
      "type": "text"
    },
    {
      "q": "4,500 ÷ 100 = ?",
      "a": "45",
      "type": "text"
    },
    {
      "q": "40 × 30 = ?",
      "a": "1200",
      "type": "text"
    },
    {
      "q": "120 × 20 = ?",
      "a": "2400",
      "type": "text"
    },
    {
      "q": "60 × 300 = ?",
      "a": "18000",
      "type": "text"
    },
    {
      "q": "50 × 70 = ?",
      "a": "3500",
      "type": "text"
    },
    {
      "q": "80 × 90 = ?",
      "a": "7200",
      "type": "text"
    },
    {
      "q": "200 × 40 = ?",
      "a": "8000",
      "type": "text"
    },
    {
      "q": "30 × 60 = ?",
      "a": "1800",
      "type": "text"
    },
    {
      "q": "70 × 80 = ?",
      "a": "5600",
      "type": "text"
    },
    {
      "q": "90 × 50 = ?",
      "a": "4500",
      "type": "text"
    },
    {
      "q": "300 × 20 = ?",
      "a": "6000",
      "type": "text"
    },
    {
      "q": "8 × 83 = ? (פרקי ל-80 + 3)",
      "a": "664",
      "type": "text"
    },
    {
      "q": "203 × 5 = ?",
      "a": "1015",
      "type": "text"
    },
    {
      "q": "344 × 2 = ?",
      "a": "688",
      "type": "text"
    },
    {
      "q": "8 × 39 = ?",
      "a": "312",
      "type": "text"
    },
    {
      "q": "175 × 4 = ?",
      "a": "700",
      "type": "text"
    },
    {
      "q": "199 × 3 = ?",
      "a": "597",
      "type": "text"
    },
    {
      "q": "6 × 47 = ?",
      "a": "282",
      "type": "text"
    },
    {
      "q": "125 × 8 = ?",
      "a": "1000",
      "type": "text"
    },
    {
      "q": "9 × 56 = ?",
      "a": "504",
      "type": "text"
    },
    {
      "q": "234 × 3 = ?",
      "a": "702",
      "type": "text"
    },
    {
      "q": "6,000 ÷ 20 = ?",
      "a": "300",
      "type": "text"
    },
    {
      "q": "3,000 ÷ 50 = ?",
      "a": "60",
      "type": "text"
    },
    {
      "q": "120 ÷ 60 = ?",
      "a": "2",
      "type": "text"
    },
    {
      "q": "2,400 ÷ 60 = ?",
      "a": "40",
      "type": "text"
    },
    {
      "q": "4,500 ÷ 90 = ?",
      "a": "50",
      "type": "text"
    },
    {
      "q": "8,000 ÷ 200 = ?",
      "a": "40",
      "type": "text"
    },
    {
      "q": "3,600 ÷ 90 = ?",
      "a": "40",
      "type": "text"
    },
    {
      "q": "7,000 ÷ 100 = ?",
      "a": "70",
      "type": "text"
    },
    {
      "q": "בקופה היו 350 מטבעות של 10 שקלים. כמה כסף היה בקופה? (בשקלים)",
      "a": "3500",
      "type": "text"
    },
    {
      "q": "בחנות קנו 15 שמלות ב-100 שקלים כל אחת. כמה עלו כל השמלות? (בשקלים)",
      "a": "1500",
      "type": "text"
    },
    {
      "q": "יש 8 קבוצות של תלמידים. בכל קבוצה 35 תלמידים. כמה תלמידים בסך הכל?",
      "a": "280",
      "type": "text"
    },
    {
      "q": "לטיול יצאו 6 אוטובוסים עם 45 תלמידים בכל אוטובוס. כמה תלמידים יצאו לטיול?",
      "a": "270",
      "type": "text"
    },
    {
      "q": "במפעל מייצרים 125 מוצרים בשעה. כמה מוצרים ייצרו ב-8 שעות?",
      "a": "1000",
      "type": "text"
    },
    {
      "q": "בספריה יש 12 מדפים. בכל מדף 48 ספרים. כמה ספרים יש בספריה?",
      "a": "576",
      "type": "text"
    },
    {
      "q": "בבית הספר יש 9 כיתות עם 32 תלמידים בכל כיתה. כמה תלמידים יש בבית הספר?",
      "a": "288",
      "type": "text"
    },
    {
      "q": "חנות מכרה 25 חולצות ב-80 שקלים כל אחת. כמה כסף הרוויחה? (בשקלים)",
      "a": "2000",
      "type": "text"
    },
    {
      "q": "כתבי < או > או = : 45 × 1 ___ 45 ÷ 1",
      "a": "=",
      "type": "text"
    },
    {
      "q": "כתבי < או > או = : 8,000 ÷ 18 ___ 8,000 ÷ 12",
      "a": "<",
      "type": "text"
    },
    {
      "q": "כתבי < או > או = : 63 × 52 ___ 52 × 63",
      "a": "=",
      "type": "text"
    },
    {
      "q": "כתבי < או > או = : 200 × 410 ___ 2,000 × 41",
      "a": "=",
      "type": "text"
    },
    {
      "q": "כתבי < או > או = : 200 × 10 ___ 200 × 5",
      "a": ">",
      "type": "text"
    },
    {
      "q": "כתבי < או > או = : 200 ÷ 100 ___ 2,000 ÷ 1,000",
      "a": "=",
      "type": "text"
    },
    {
      "q": "כתבי < או > או = : 10/3 ___ 3",
      "a": ">",
      "type": "text"
    },
    {
      "q": "כתבי < או > או = : 3 5/6 ___ 20/6",
      "a": ">",
      "type": "text"
    },
    {
      "q": "כתבי < או > או = : 4 35/100 ___ 4 7/100",
      "a": ">",
      "type": "text"
    }
  ]
}
